pyliwc/__init__.py
pyliwc/_modidx.py
pyliwc/core.py
pyliwc-1.5.dist-info/licenses/LICENSE
pyliwc-1.5.dist-info/METADATA
pyliwc-1.5.dist-info/WHEEL
pyliwc-1.5.dist-info/entry_points.txt
pyliwc-1.5.dist-info/top_level.txt
pyliwc-1.5.dist-info/RECORD
