Metadata-Version: 2.4
Name: pyliwc
Version: 1.5
Summary: Linguistic Inquiry and Word Count (LIWC) in Python
Home-page: https://github.com/camille1/pyliwc.git
Author: C.Lacan
Author-email: camille.lacan@univ-perp.fr
License: MIT License
Keywords: LIWC "Linguistic Inquiry" "Textual Analysis" "Language Style Matching"
Classifier: Development Status :: 4 - Beta
Classifier: Intended Audience :: Developers
Classifier: Natural Language :: English
Classifier: Programming Language :: Python :: 3.7
Classifier: Programming Language :: Python :: 3.8
Classifier: Programming Language :: Python :: 3.9
Classifier: Programming Language :: Python :: 3.10
Classifier: License :: OSI Approved :: MIT License
Requires-Python: >=3.7
License-File: LICENSE
Requires-Dist: pandas
Requires-Dist: matplotlib
Provides-Extra: dev
Requires-Dist: fastcore; extra == "dev"
Dynamic: author
Dynamic: author-email
Dynamic: classifier
Dynamic: description
Dynamic: description-content-type
Dynamic: home-page
Dynamic: keywords
Dynamic: license
Dynamic: license-file
Dynamic: provides-extra
Dynamic: requires-dist
Dynamic: requires-python
Dynamic: summary
